21cmpsdenoiser-1.0.2.dist-info/licenses/LICENSE
psdenoiser/__init__.py
psdenoiser/_version.py
psdenoiser/constants.npz
psdenoiser/denoiser.py
psdenoiser/denoiser_model.pt
psdenoiser/inputs.py
psdenoiser/model.py
psdenoiser/model_utils.py
psdenoiser/outputs.py
psdenoiser/properties.py
psdenoiser/sample_pytorch.py
psdenoiser/sde.py
psdenoiser/test_denoiser.py
psdenoiser/utils.py
psdenoiser/training/loss.py
21cmpsdenoiser-1.0.2.dist-info/METADATA
21cmpsdenoiser-1.0.2.dist-info/WHEEL
21cmpsdenoiser-1.0.2.dist-info/top_level.txt
21cmpsdenoiser-1.0.2.dist-info/RECORD
